Metadata-Version: 2.1
Name: slurmee
Version: 0.1.0rc3
Summary: Simple Python 3 package to get information when running Python programs in slurm
Home-page: https://github.com/jcklie/slurmee
Author: Jan-Christoph Klie
Author-email: git@mrklie.com
License: MIT License
Project-URL: Bug Tracker, https://github.com/jcklie/slurmee/issues
Project-URL: Documentation, https://github.com/jcklie/slurmee
Project-URL: Source Code, https://github.com/jcklie/slurmee
Keywords: slurm
Platform: UNKNOWN
Classifier: Development Status :: 4 - Beta
Classifier: Intended Audience :: Developers
Classifier: Intended Audience :: Science/Research
Classifier: License :: OSI Approved :: MIT License
Classifier: Programming Language :: Python :: 3 :: Only
Classifier: Programming Language :: Python :: 3.5
Classifier: Programming Language :: Python :: 3.6
Classifier: Programming Language :: Python :: 3.7
Classifier: Topic :: Software Development :: Libraries
Classifier: Topic :: Scientific/Engineering
Classifier: Topic :: System :: Distributed Computing
Requires-Python: >=3.5.0
Provides-Extra: doc
Provides-Extra: test
Provides-Extra: dev
